[
  {
    "Codice": 100000301,
    "Descrizione": "AFGHANISTAN",
    "Provincia": "ES",
    "DataFineVal": "",
    "ISO": "AFG"
  },
  {
    "Codice": 100000201,
    "Descrizione": "ALBANIA",
    "Provincia": "ES",
    "DataFineVal": "",
    "ISO": "ALB"
  },
  {
    "Codice": 100000401,
    "Descrizione": "ALGERIA",
    "Provincia": "ES",
    "DataFineVal": "",
    "ISO": "DZA"
  },
  {
    "Codice": 100000202,
    "Descrizione": "ANDORRA",
    "Provincia": "ES",
    "DataFineVal": "",
    "ISO": "AND"
  },
  {
    "Codice": 100000402,
    "Descrizione": "ANGOLA",
    "Provincia": "ES",
    "DataFineVal": "",
    "ISO": "AGO"
  },
  {
    "Codice": 100000733,
    "Descrizione": "ANGUILLA (ISOLA)",
    "Provincia": "ES",
    "DataFineVal": "",
    "ISO": "AIA"
  },
  {
    "Codice": 100000503,
    "Descrizione": "ANTIGUA E BARBUDA",
    "Provincia": "ES",
    "DataFineVal": "",
    "ISO": "ATG"
  },
  {
    "Codice": 100000999,
    "Descrizione": "APOLIDE",
    "Provincia": "ES",
    "DataFineVal": "",
    "ISO": "APO"
  },
  {
    "Codice": 100000302,
    "Descrizione": "ARABIA SAUDITA",
    "Provincia": "ES",
    "DataFineVal": "",
    "ISO": "SAU"
  },
  {
    "Codice": 100000602,
    "Descrizione": "ARGENTINA",
    "Provincia": "ES",
    "DataFineVal": "",
    "ISO": "ARG"
  },
  {
    "Codice": 100000358,
    "Descrizione": "ARMENIA",
    "Provincia": "ES",
    "DataFineVal": "",
    "ISO": "ARM"
  },
  {
    "Codice": 100000701,
    "Descrizione": "AUSTRALIA",
    "Provincia": "ES",
    "DataFineVal": "",
    "ISO": "AUS"
  },
  {
    "Codice": 100000203,
    "Descrizione": "AUSTRIA",
    "Provincia": "ES",
    "DataFineVal": "",
    "ISO": "AUT"
  },
  {
    "Codice": 100000359,
    "Descrizione": "AZERBAIGIAN",
    "Provincia": "ES",
    "DataFineVal": "",
    "ISO": "AZE"
  },
  {
    "Codice": 100000505,
    "Descrizione": "BAHAMAS",
    "Provincia": "ES",
    "DataFineVal": "",
    "ISO": "BHS"
  },
  {
    "Codice": 100000304,
    "Descrizione": "BAHREIN",
    "Provincia": "ES",
    "DataFineVal": "",
    "ISO": "BHR"
  },
  {
    "Codice": 100000305,
    "Descrizione": "BANGLADESH",
    "Provincia": "ES",
    "DataFineVal": "",
    "ISO": "BGD"
  },
  {
    "Codice": 100000506,
    "Descrizione": "BARBADOS",
    "Provincia": "ES",
    "DataFineVal": "",
    "ISO": "BRB"
  },
  {
    "Codice": 100000206,
    "Descrizione": "BELGIO",
    "Provincia": "ES",
    "DataFineVal": "",
    "ISO": "BEL"
  },
  {
    "Codice": 100000507,
    "Descrizione": "BELIZE",
    "Provincia": "ES",
    "DataFineVal": "",
    "ISO": "BLZ"
  },
  {
    "Codice": 100000406,
    "Descrizione": "BENIN",
    "Provincia": "ES",
    "DataFineVal": "",
    "ISO": "BEN"
  },
  {
    "Codice": 100000739,
    "Descrizione": "BERMUDE",
    "Provincia": "ES",
    "DataFineVal": "",
    "ISO": "BMU"
  },
  {
    "Codice": 100000306,
    "Descrizione": "BHUTAN",
    "Provincia": "ES",
    "DataFineVal": "",
    "ISO": "BTN"
  },
  {
    "Codice": 100000256,
    "Descrizione": "BIELORUSSIA",
    "Provincia": "ES",
    "DataFineVal": "",
    "ISO": "BLR"
  },
  {
    "Codice": 100000604,
    "Descrizione": "BOLIVIA",
    "Provincia": "ES",
    "DataFineVal": "",
    "ISO": "BOL"
  },
  {
    "Codice": 100000740,
    "Descrizione": "BOPHUTHATSWANA",
    "Provincia": "ES",
    "DataFineVal": "01/05/1994 00:00:00",
    "ISO": "BOP"
  },
  {
    "Codice": 100000252,
    "Descrizione": "BOSNIA ED ERZEGOVINA",
    "Provincia": "ES",
    "DataFineVal": "",
    "ISO": "BIH"
  },
  {
    "Codice": 100000408,
    "Descrizione": "BOTSWANA",
    "Provincia": "ES",
    "DataFineVal": "",
    "ISO": "BWA"
  },
  {
    "Codice": 100000605,
    "Descrizione": "BRASILE",
    "Provincia": "ES",
    "DataFineVal": "",
    "ISO": "BRA"
  },
  {
    "Codice": 100000309,
    "Descrizione": "BRUNEI DARUSSALAM",
    "Provincia": "ES",
    "DataFineVal": "",
    "ISO": "BRN"
  },
  {
    "Codice": 100000209,
    "Descrizione": "BULGARIA",
    "Provincia": "ES",
    "DataFineVal": "",
    "ISO": "BGR"
  },
  {
    "Codice": 100000409,
    "Descrizione": "BURKINA FASO",
    "Provincia": "ES",
    "DataFineVal": "",
    "ISO": "BFA"
  },
  {
    "Codice": 100000410,
    "Descrizione": "BURUNDI",
    "Provincia": "ES",
    "DataFineVal": "",
    "ISO": "BDI"
  },
  {
    "Codice": 100000310,
    "Descrizione": "CAMBOGIA",
    "Provincia": "ES",
    "DataFineVal": "",
    "ISO": "KHM"
  },
  {
    "Codice": 100000411,
    "Descrizione": "CAMERUN",
    "Provincia": "ES",
    "DataFineVal": "",
    "ISO": "CMR"
  },
  {
    "Codice": 100000509,
    "Descrizione": "CANADA",
    "Provincia": "ES",
    "DataFineVal": "",
    "ISO": "CAN"
  },
  {
    "Codice": 100000413,
    "Descrizione": "CAPO VERDE",
    "Provincia": "ES",
    "DataFineVal": "",
    "ISO": "CPV"
  },
  {
    "Codice": 100000742,
    "Descrizione": "CAYMAN (ISOLE)",
    "Provincia": "ES",
    "DataFineVal": "",
    "ISO": "CYM"
  },
  {
    "Codice": 100000210,
    "Descrizione": "CECOSLOVACCHIA",
    "Provincia": "ES",
    "DataFineVal": "01/01/1993 00:00:00",
    "ISO": "CZE"
  },
  {
    "Codice": 100000743,
    "Descrizione": "CHRISTMAS",
    "Provincia": "ES",
    "DataFineVal": "",
    "ISO": "ITA"
  },
  {
    "Codice": 100000415,
    "Descrizione": "CIAD",
    "Provincia": "ES",
    "DataFineVal": "",
    "ISO": "ITA"
  },
  {
    "Codice": 100000606,
    "Descrizione": "CILE",
    "Provincia": "ES",
    "DataFineVal": "",
    "ISO": "CIV"
  },
  {
    "Codice": 100000314,
    "Descrizione": "CINA",
    "Provincia": "ES",
    "DataFineVal": "",
    "ISO": "CHN"
  },
  {
    "Codice": 100000315,
    "Descrizione": "CIPRO",
    "Provincia": "ES",
    "DataFineVal": "",
    "ISO": "CIP"
  },
  {
    "Codice": 100000746,
    "Descrizione": "COCOS",
    "Provincia": "ES",
    "DataFineVal": "",
    "ISO": "CCK"
  },
  {
    "Codice": 100000608,
    "Descrizione": "COLOMBIA",
    "Provincia": "ES",
    "DataFineVal": "",
    "ISO": "COL"
  },
  {
    "Codice": 100000417,
    "Descrizione": "COMORE",
    "Provincia": "ES",
    "DataFineVal": "",
    "ISO": "COM"
  },
  {
    "Codice": 100000418,
    "Descrizione": "CONGO",
    "Provincia": "ES",
    "DataFineVal": "",
    "ISO": "COD"
  },
  {
    "Codice": 100000319,
    "Descrizione": "COREA DEL NORD",
    "Provincia": "ES",
    "DataFineVal": "",
    "ISO": "PRK"
  },
  {
    "Codice": 100000320,
    "Descrizione": "COREA DEL SUD",
    "Provincia": "ES",
    "DataFineVal": "",
    "ISO": "KOR"
  },
  {
    "Codice": 100000404,
    "Descrizione": "COSTA D'AVORIO",
    "Provincia": "ES",
    "DataFineVal": "",
    "ISO": "CIV"
  },
  {
    "Codice": 100000513,
    "Descrizione": "COSTA RICA",
    "Provincia": "ES",
    "DataFineVal": "",
    "ISO": "CRI"
  },
  {
    "Codice": 100000250,
    "Descrizione": "CROAZIA",
    "Provincia": "ES",
    "DataFineVal": "",
    "ISO": "HRV"
  },
  {
    "Codice": 100000514,
    "Descrizione": "CUBA",
    "Provincia": "ES",
    "DataFineVal": "",
    "ISO": "CUB"
  },
  {
    "Codice": 100000212,
    "Descrizione": "DANIMARCA",
    "Provincia": "ES",
    "DataFineVal": "",
    "ISO": "DNK"
  },
  {
    "Codice": 100000515,
    "Descrizione": "DOMINICA",
    "Provincia": "ES",
    "DataFineVal": "",
    "ISO": "DMA"
  },
  {
    "Codice": 100000609,
    "Descrizione": "ECUADOR",
    "Provincia": "ES",
    "DataFineVal": "",
    "ISO": "ECU"
  },
  {
    "Codice": 100000419,
    "Descrizione": "EGITTO",
    "Provincia": "ES",
    "DataFineVal": "",
    "ISO": "EGY"
  },
  {
    "Codice": 100000517,
    "Descrizione": "EL SALVADOR",
    "Provincia": "ES",
    "DataFineVal": "",
    "ISO": "SLV"
  },
  {
    "Codice": 100000322,
    "Descrizione": "EMIRATI ARABI UNITI",
    "Provincia": "ES",
    "DataFineVal": "",
    "ISO": "ARE"
  },
  {
    "Codice": 100000466,
    "Descrizione": "ERITREA",
    "Provincia": "ES",
    "DataFineVal": "",
    "ISO": "ERI"
  },
  {
    "Codice": 100000247,
    "Descrizione": "ESTONIA",
    "Provincia": "ES",
    "DataFineVal": "",
    "ISO": "EST"
  },
  {
    "Codice": 100000420,
    "Descrizione": "ETIOPIA",
    "Provincia": "ES",
    "DataFineVal": "",
    "ISO": "ETH"
  },
  {
    "Codice": 100000755,
    "Descrizione": "FAER OER",
    "Provincia": "ES",
    "DataFineVal": "",
    "ISO": "FRA"
  },
  {
    "Codice": 100000245,
    "Descrizione": "FEDERAZIONE RUSSA",
    "Provincia": "ES",
    "DataFineVal": "",
    "ISO": "RUS"
  },
  {
    "Codice": 100000703,
    "Descrizione": "FIGI",
    "Provincia": "ES",
    "DataFineVal": "",
    "ISO": "FIG"
  },
  {
    "Codice": 100000323,
    "Descrizione": "FILIPPINE",
    "Provincia": "ES",
    "DataFineVal": "",
    "ISO": "PHL"
  },
  {
    "Codice": 100000214,
    "Descrizione": "FINLANDIA",
    "Provincia": "ES",
    "DataFineVal": "",
    "ISO": "FIN"
  },
  {
    "Codice": 100000215,
    "Descrizione": "FRANCIA",
    "Provincia": "ES",
    "DataFineVal": "",
    "ISO": "FRA"
  },
  {
    "Codice": 100000421,
    "Descrizione": "GABON",
    "Provincia": "ES",
    "DataFineVal": "",
    "ISO": "GAB"
  },
  {
    "Codice": 100000422,
    "Descrizione": "GAMBIA",
    "Provincia": "ES",
    "DataFineVal": "",
    "ISO": "GMB"
  },
  {
    "Codice": 100000360,
    "Descrizione": "GEORGIA",
    "Provincia": "ES",
    "DataFineVal": "",
    "ISO": "GEO"
  },
  {
    "Codice": 110000022,
    "Descrizione": "GEORGIA SUD E ISOLE SANDWICH AUSTRALI",
    "Provincia": "ES",
    "DataFineVal": "",
    "ISO": "AUS"
  },
  {
    "Codice": 100000216,
    "Descrizione": "GERMANIA",
    "Provincia": "ES",
    "DataFineVal": "",
    "ISO": "DEU"
  },
  {
    "Codice": 100000423,
    "Descrizione": "GHANA",
    "Provincia": "ES",
    "DataFineVal": "",
    "ISO": "GHA"
  },
  {
    "Codice": 100000518,
    "Descrizione": "GIAMAICA",
    "Provincia": "ES",
    "DataFineVal": "",
    "ISO": "JAM"
  },
  {
    "Codice": 100000326,
    "Descrizione": "GIAPPONE",
    "Provincia": "ES",
    "DataFineVal": "",
    "ISO": "JPN"
  },
  {
    "Codice": 100000424,
    "Descrizione": "GIBUTI",
    "Provincia": "ES",
    "DataFineVal": "",
    "ISO": "DJI"
  },
  {
    "Codice": 100000327,
    "Descrizione": "GIORDANIA",
    "Provincia": "ES",
    "DataFineVal": "",
    "ISO": "JOR"
  },
  {
    "Codice": 100000220,
    "Descrizione": "GRECIA",
    "Provincia": "ES",
    "DataFineVal": "",
    "ISO": "GRC"
  },
  {
    "Codice": 100000519,
    "Descrizione": "GRENADA",
    "Provincia": "ES",
    "DataFineVal": "",
    "ISO": "GRD"
  },
  {
    "Codice": 100000758,
    "Descrizione": "GROENLANDIA",
    "Provincia": "ES",
    "DataFineVal": "",
    "ISO": "GRL"
  },
  {
    "Codice": 100000759,
    "Descrizione": "GUADALUPA",
    "Provincia": "ES",
    "DataFineVal": "",
    "ISO": "GUM"
  },
  {
    "Codice": 100000760,
    "Descrizione": "GUAM",
    "Provincia": "ES",
    "DataFineVal": "",
    "ISO": "GUM"
  },
  {
    "Codice": 100000523,
    "Descrizione": "GUATEMALA",
    "Provincia": "ES",
    "DataFineVal": "",
    "ISO": "GTM"
  },
  {
    "Codice": 100000761,
    "Descrizione": "GUAYANA FRANCESE",
    "Provincia": "ES",
    "DataFineVal": "",
    "ISO": "GUF"
  },
  {
    "Codice": 110000014,
    "Descrizione": "GUERNSEY",
    "Provincia": "ES",
    "DataFineVal": "",
    "ISO": "GGY"
  },
  {
    "Codice": 100000425,
    "Descrizione": "GUINEA",
    "Provincia": "ES",
    "DataFineVal": "",
    "ISO": "GIN"
  },
  {
    "Codice": 100000426,
    "Descrizione": "GUINEA BISSAU",
    "Provincia": "ES",
    "DataFineVal": "",
    "ISO": "GNB"
  },
  {
    "Codice": 100000427,
    "Descrizione": "GUINEA EQUATORIALE",
    "Provincia": "ES",
    "DataFineVal": "",
    "ISO": "GNQ"
  },
  {
    "Codice": 100000612,
    "Descrizione": "GUYANA",
    "Provincia": "ES",
    "DataFineVal": "",
    "ISO": "GUY"
  },
  {
    "Codice": 100000524,
    "Descrizione": "HAITI",
    "Provincia": "ES",
    "DataFineVal": "",
    "ISO": "HTI"
  },
  {
    "Codice": 100000525,
    "Descrizione": "HONDURAS",
    "Provincia": "ES",
    "DataFineVal": "",
    "ISO": "HND"
  },
  {
    "Codice": 110000005,
    "Descrizione": "HONG KONG",
    "Provincia": "ES",
    "DataFineVal": "",
    "ISO": "HKG"
  },
  {
    "Codice": 100000330,
    "Descrizione": "INDIA",
    "Provincia": "ES",
    "DataFineVal": "",
    "ISO": "IND"
  },
  {
    "Codice": 100000331,
    "Descrizione": "INDONESIA",
    "Provincia": "ES",
    "DataFineVal": "",
    "ISO": "IDN"
  },
  {
    "Codice": 100000332,
    "Descrizione": "IRAN",
    "Provincia": "ES",
    "DataFineVal": "",
    "ISO": "IRN"
  },
  {
    "Codice": 100000333,
    "Descrizione": "IRAQ",
    "Provincia": "ES",
    "DataFineVal": "",
    "ISO": "IRQ"
  },
  {
    "Codice": 100000221,
    "Descrizione": "IRLANDA",
    "Provincia": "ES",
    "DataFineVal": "",
    "ISO": "IRL"
  },
  {
    "Codice": 100000223,
    "Descrizione": "ISLANDA",
    "Provincia": "ES",
    "DataFineVal": "",
    "ISO": "ISL"
  },
  {
    "Codice": 100000764,
    "Descrizione": "ISOLE VERGINI",
    "Provincia": "ES",
    "DataFineVal": "",
    "ISO": "VIR"
  },
  {
    "Codice": 100000334,
    "Descrizione": "ISRAELE",
    "Provincia": "ES",
    "DataFineVal": "",
    "ISO": "ISR"
  },
  {
    "Codice": 100000100,
    "Descrizione": "ITALIA",
    "Provincia": "ES",
    "DataFineVal": "",
    "ISO": "ITA"
  },
  {
    "Codice": 100000356,
    "Descrizione": "KAZAKISTAN",
    "Provincia": "ES",
    "DataFineVal": "",
    "ISO": "KAZ"
  },
  {
    "Codice": 100000428,
    "Descrizione": "KENYA",
    "Provincia": "ES",
    "DataFineVal": "",
    "ISO": "KEN"
  },
  {
    "Codice": 100000361,
    "Descrizione": "KIRGHIZISTAN",
    "Provincia": "ES",
    "DataFineVal": "",
    "ISO": "KGZ"
  },
  {
    "Codice": 100000708,
    "Descrizione": "KIRIBATI",
    "Provincia": "ES",
    "DataFineVal": "",
    "ISO": "KIR"
  },
  {
    "Codice": 100001002,
    "Descrizione": "KOSOVO",
    "Provincia": "ES",
    "DataFineVal": "",
    "ISO": "XKX"
  },
  {
    "Codice": 100000335,
    "Descrizione": "KUWAIT",
    "Provincia": "ES",
    "DataFineVal": "",
    "ISO": "KWT"
  },
  {
    "Codice": 100000765,
    "Descrizione": "LA REUNION",
    "Provincia": "ES",
    "DataFineVal": "",
    "ISO": "REU"
  },
  {
    "Codice": 100000336,
    "Descrizione": "LAOS",
    "Provincia": "ES",
    "DataFineVal": "",
    "ISO": "LAO"
  },
  {
    "Codice": 100000429,
    "Descrizione": "LESOTHO",
    "Provincia": "ES",
    "DataFineVal": "",
    "ISO": "LSO"
  },
  {
    "Codice": 100000248,
    "Descrizione": "LETTONIA",
    "Provincia": "ES",
    "DataFineVal": "",
    "ISO": "LVA"
  },
  {
    "Codice": 100000337,
    "Descrizione": "LIBANO",
    "Provincia": "ES",
    "DataFineVal": "",
    "ISO": "LBN"
  },
  {
    "Codice": 100000430,
    "Descrizione": "LIBERIA",
    "Provincia": "ES",
    "DataFineVal": "",
    "ISO": "LBR"
  },
  {
    "Codice": 100000431,
    "Descrizione": "LIBIA",
    "Provincia": "ES",
    "DataFineVal": "",
    "ISO": "LBY"
  },
  {
    "Codice": 100000225,
    "Descrizione": "LIECHTENSTEIN",
    "Provincia": "ES",
    "DataFineVal": "",
    "ISO": "LIE"
  },
  {
    "Codice": 100000249,
    "Descrizione": "LITUANIA",
    "Provincia": "ES",
    "DataFineVal": "",
    "ISO": "LTU"
  },
  {
    "Codice": 100000226,
    "Descrizione": "LUSSEMBURGO",
    "Provincia": "ES",
    "DataFineVal": "",
    "ISO": "LUX"
  },
  {
    "Codice": 110000003,
    "Descrizione": "MACAO",
    "Provincia": "ES",
    "DataFineVal": "",
    "ISO": "MAC"
  },
  {
    "Codice": 100000253,
    "Descrizione": "MACEDONIA",
    "Provincia": "ES",
    "DataFineVal": "13/02/2019 00:00:00",
    "ISO": "MKD"
  },
  {
    "Codice": 100000997,
    "Descrizione": "MACEDONIA DEL NORD",
    "Provincia": "ES",
    "DataFineVal": "",
    "ISO": "MKD"
  },
  {
    "Codice": 100000432,
    "Descrizione": "MADAGASCAR",
    "Provincia": "ES",
    "DataFineVal": "",
    "ISO": "MDG"
  },
  {
    "Codice": 100000434,
    "Descrizione": "MALAWI",
    "Provincia": "ES",
    "DataFineVal": "",
    "ISO": "MWI"
  },
  {
    "Codice": 100000767,
    "Descrizione": "MALAYSIA",
    "Provincia": "ES",
    "DataFineVal": "",
    "ISO": "MYS"
  },
  {
    "Codice": 100000339,
    "Descrizione": "MALDIVE",
    "Provincia": "ES",
    "DataFineVal": "",
    "ISO": "MDV"
  },
  {
    "Codice": 100000435,
    "Descrizione": "MALI",
    "Provincia": "ES",
    "DataFineVal": "",
    "ISO": "MLI"
  },
  {
    "Codice": 100000227,
    "Descrizione": "MALTA",
    "Provincia": "ES",
    "DataFineVal": "",
    "ISO": "MLT"
  },
  {
    "Codice": 100000768,
    "Descrizione": "MALVINE",
    "Provincia": "ES",
    "DataFineVal": "",
    "ISO": "MLV"
  },
  {
    "Codice": 100000769,
    "Descrizione": "MAN",
    "Provincia": "ES",
    "DataFineVal": "",
    "ISO": "MNG"
  },
  {
    "Codice": 100000436,
    "Descrizione": "MAROCCO",
    "Provincia": "ES",
    "DataFineVal": "",
    "ISO": "MAR"
  },
  {
    "Codice": 100000772,
    "Descrizione": "MARSHALL",
    "Provincia": "ES",
    "DataFineVal": "",
    "ISO": "MHL"
  },
  {
    "Codice": 100000773,
    "Descrizione": "MARTINICA",
    "Provincia": "ES",
    "DataFineVal": "",
    "ISO": "MTQ"
  },
  {
    "Codice": 100000437,
    "Descrizione": "MAURITANIA",
    "Provincia": "ES",
    "DataFineVal": "",
    "ISO": "MRT"
  },
  {
    "Codice": 100000438,
    "Descrizione": "MAURIZIO",
    "Provincia": "ES",
    "DataFineVal": "",
    "ISO": "ITA"
  },
  {
    "Codice": 100000774,
    "Descrizione": "MAYOTTE",
    "Provincia": "ES",
    "DataFineVal": "",
    "ISO": "MYT"
  },
  {
    "Codice": 100000527,
    "Descrizione": "MESSICO",
    "Provincia": "ES",
    "DataFineVal": "",
    "ISO": "MEX"
  },
  {
    "Codice": 100000775,
    "Descrizione": "MICRONESIA STATI FEDERALI",
    "Provincia": "ES",
    "DataFineVal": "",
    "ISO": "FSM"
  },
  {
    "Codice": 100000254,
    "Descrizione": "MOLDAVIA",
    "Provincia": "ES",
    "DataFineVal": "",
    "ISO": "MDA"
  },
  {
    "Codice": 100000229,
    "Descrizione": "MONACO",
    "Provincia": "ES",
    "DataFineVal": "",
    "ISO": "MCO"
  },
  {
    "Codice": 100000341,
    "Descrizione": "MONGOLIA",
    "Provincia": "ES",
    "DataFineVal": "",
    "ISO": "MNG"
  },
  {
    "Codice": 100001001,
    "Descrizione": "MONTENEGRO",
    "Provincia": "ES",
    "DataFineVal": "",
    "ISO": "MNE"
  },
  {
    "Codice": 100000777,
    "Descrizione": "MONTSERRAT",
    "Provincia": "ES",
    "DataFineVal": "",
    "ISO": "MSR"
  },
  {
    "Codice": 100000440,
    "Descrizione": "MOZAMBICO",
    "Provincia": "ES",
    "DataFineVal": "",
    "ISO": "MOZ"
  },
  {
    "Codice": 100000307,
    "Descrizione": "MYANMAR-BIRMANIA",
    "Provincia": "ES",
    "DataFineVal": "",
    "ISO": "MMR"
  },
  {
    "Codice": 100000441,
    "Descrizione": "NAMIBIA",
    "Provincia": "ES",
    "DataFineVal": "",
    "ISO": "NAM"
  },
  {
    "Codice": 100000715,
    "Descrizione": "NAURU",
    "Provincia": "ES",
    "DataFineVal": "",
    "ISO": "NRU"
  },
  {
    "Codice": 100000342,
    "Descrizione": "NEPAL",
    "Provincia": "ES",
    "DataFineVal": "",
    "ISO": "NPL"
  },
  {
    "Codice": 100000529,
    "Descrizione": "NICARAGUA",
    "Provincia": "ES",
    "DataFineVal": "",
    "ISO": "NIC"
  },
  {
    "Codice": 100000442,
    "Descrizione": "NIGER",
    "Provincia": "ES",
    "DataFineVal": "",
    "ISO": "NER"
  },
  {
    "Codice": 100000443,
    "Descrizione": "NIGERIA",
    "Provincia": "ES",
    "DataFineVal": "",
    "ISO": "NGA"
  },
  {
    "Codice": 100000778,
    "Descrizione": "NORFOLK",
    "Provincia": "ES",
    "DataFineVal": "",
    "ISO": "GBR"
  },
  {
    "Codice": 100000231,
    "Descrizione": "NORVEGIA",
    "Provincia": "ES",
    "DataFineVal": "",
    "ISO": "NOR"
  },
  {
    "Codice": 100000780,
    "Descrizione": "NUOVA CALEDONIA",
    "Provincia": "ES",
    "DataFineVal": "",
    "ISO": "NCL"
  },
  {
    "Codice": 100000719,
    "Descrizione": "NUOVA ZELANDA",
    "Provincia": "ES",
    "DataFineVal": "",
    "ISO": "NZL"
  },
  {
    "Codice": 100000343,
    "Descrizione": "OMAN",
    "Provincia": "ES",
    "DataFineVal": "",
    "ISO": "OMN"
  },
  {
    "Codice": 100000232,
    "Descrizione": "PAESI BASSI",
    "Provincia": "ES",
    "DataFineVal": "",
    "ISO": "NLD"
  },
  {
    "Codice": 100000344,
    "Descrizione": "PAKISTAN",
    "Provincia": "ES",
    "DataFineVal": "",
    "ISO": "PAK"
  },
  {
    "Codice": 100000783,
    "Descrizione": "PALAU REPUBBLICA",
    "Provincia": "ES",
    "DataFineVal": "",
    "ISO": "PLW"
  },
  {
    "Codice": 110000001,
    "Descrizione": "PALESTINA",
    "Provincia": "ES",
    "DataFineVal": "",
    "ISO": "PSE"
  },
  {
    "Codice": 100000530,
    "Descrizione": "PANAMA",
    "Provincia": "ES",
    "DataFineVal": "",
    "ISO": "PAN"
  },
  {
    "Codice": 100000721,
    "Descrizione": "PAPUASIA-N.GUINEA",
    "Provincia": "ES",
    "DataFineVal": "",
    "ISO": "PNG"
  },
  {
    "Codice": 100000614,
    "Descrizione": "PARAGUAY",
    "Provincia": "ES",
    "DataFineVal": "",
    "ISO": "PRY"
  },
  {
    "Codice": 100000615,
    "Descrizione": "PERU'",
    "Provincia": "ES",
    "DataFineVal": "",
    "ISO": "PER"
  },
  {
    "Codice": 100000786,
    "Descrizione": "PITCAIRN",
    "Provincia": "ES",
    "DataFineVal": "",
    "ISO": "PCN"
  },
  {
    "Codice": 100000787,
    "Descrizione": "POLINESIA",
    "Provincia": "ES",
    "DataFineVal": "",
    "ISO": "PYF"
  },
  {
    "Codice": 100000233,
    "Descrizione": "POLONIA",
    "Provincia": "ES",
    "DataFineVal": "",
    "ISO": "POL"
  },
  {
    "Codice": 100000234,
    "Descrizione": "PORTOGALLO",
    "Provincia": "ES",
    "DataFineVal": "",
    "ISO": "PRT"
  },
  {
    "Codice": 100000790,
    "Descrizione": "PUERTO RICO",
    "Provincia": "ES",
    "DataFineVal": "",
    "ISO": "PRI"
  },
  {
    "Codice": 100000345,
    "Descrizione": "QATAR",
    "Provincia": "ES",
    "DataFineVal": "",
    "ISO": "QAT"
  },
  {
    "Codice": 100000219,
    "Descrizione": "REGNO UNITO",
    "Provincia": "ES",
    "DataFineVal": "",
    "ISO": "GBR"
  },
  {
    "Codice": 100000257,
    "Descrizione": "REPUBBLICA CECA",
    "Provincia": "ES",
    "DataFineVal": "",
    "ISO": "CZE"
  },
  {
    "Codice": 100000414,
    "Descrizione": "REPUBBLICA CENTRAFRICANA",
    "Provincia": "ES",
    "DataFineVal": "",
    "ISO": "CAF"
  },
  {
    "Codice": 100000998,
    "Descrizione": "REPUBBLICA DEMOCRATICA DEL CONGO",
    "Provincia": "ES",
    "DataFineVal": "",
    "ISO": "COD"
  },
  {
    "Codice": 100000516,
    "Descrizione": "REPUBBLICA DOMINICANA",
    "Provincia": "ES",
    "DataFineVal": "",
    "ISO": "DOM"
  },
  {
    "Codice": 100000255,
    "Descrizione": "REPUBBLICA SLOVACCA",
    "Provincia": "ES",
    "DataFineVal": "",
    "ISO": "SVK"
  },
  {
    "Codice": 100000235,
    "Descrizione": "ROMANIA",
    "Provincia": "ES",
    "DataFineVal": "",
    "ISO": "ROU"
  },
  {
    "Codice": 100000446,
    "Descrizione": "RUANDA",
    "Provincia": "ES",
    "DataFineVal": "",
    "ISO": "RWA"
  },
  {
    "Codice": 100000534,
    "Descrizione": "S. CHRISTOPHER E NEVIS",
    "Provincia": "ES",
    "DataFineVal": "",
    "ISO": "KNA"
  },
  {
    "Codice": 100000533,
    "Descrizione": "S. VINCENT E GRENADINE",
    "Provincia": "ES",
    "DataFineVal": "22/11/2001 00:00:00",
    "ISO": "VCT"
  },
  {
    "Codice": 100000795,
    "Descrizione": "SAHARA SPAGNOLO",
    "Provincia": "ES",
    "DataFineVal": "",
    "ISO": "ESP"
  },
  {
    "Codice": 100000532,
    "Descrizione": "SAINT LUCIA",
    "Provincia": "ES",
    "DataFineVal": "",
    "ISO": "LCA"
  },
  {
    "Codice": 100000796,
    "Descrizione": "SAINT PIERRE ET MIQUELON",
    "Provincia": "ES",
    "DataFineVal": "",
    "ISO": "SPM"
  },
  {
    "Codice": 100000797,
    "Descrizione": "SAINT VINCENT E GRENADINE",
    "Provincia": "ES",
    "DataFineVal": "",
    "ISO": "VCT"
  },
  {
    "Codice": 100000725,
    "Descrizione": "SALOMONE",
    "Provincia": "ES",
    "DataFineVal": "",
    "ISO": "SLV"
  },
  {
    "Codice": 100000727,
    "Descrizione": "SAMOA",
    "Provincia": "ES",
    "DataFineVal": "",
    "ISO": "WSM"
  },
  {
    "Codice": 100000798,
    "Descrizione": "SAMOA AMERICANE",
    "Provincia": "ES",
    "DataFineVal": "",
    "ISO": "WSM"
  },
  {
    "Codice": 100000236,
    "Descrizione": "SAN MARINO",
    "Provincia": "ES",
    "DataFineVal": "",
    "ISO": "SMR"
  },
  {
    "Codice": 100000799,
    "Descrizione": "SANT ELENA",
    "Provincia": "ES",
    "DataFineVal": "",
    "ISO": "ITA"
  },
  {
    "Codice": 100000448,
    "Descrizione": "SAO TOME' E PRINCIPE",
    "Provincia": "ES",
    "DataFineVal": "",
    "ISO": "STP"
  },
  {
    "Codice": 100000450,
    "Descrizione": "SENEGAL",
    "Provincia": "ES",
    "DataFineVal": "",
    "ISO": "SEN"
  },
  {
    "Codice": 100001000,
    "Descrizione": "SERBIA",
    "Provincia": "ES",
    "DataFineVal": "",
    "ISO": "SRB"
  },
  {
    "Codice": 100000449,
    "Descrizione": "SEYCHELLES",
    "Provincia": "ES",
    "DataFineVal": "",
    "ISO": "SYC"
  },
  {
    "Codice": 100000451,
    "Descrizione": "SIERRA LEONE",
    "Provincia": "ES",
    "DataFineVal": "",
    "ISO": "SLE"
  },
  {
    "Codice": 100000346,
    "Descrizione": "SINGAPORE",
    "Provincia": "ES",
    "DataFineVal": "",
    "ISO": "SGP"
  },
  {
    "Codice": 100000348,
    "Descrizione": "SIRIA",
    "Provincia": "ES",
    "DataFineVal": "",
    "ISO": "SYR"
  },
  {
    "Codice": 100000251,
    "Descrizione": "SLOVENIA",
    "Provincia": "ES",
    "DataFineVal": "",
    "ISO": "SVN"
  },
  {
    "Codice": 100000453,
    "Descrizione": "SOMALIA",
    "Provincia": "ES",
    "DataFineVal": "",
    "ISO": "SOM"
  },
  {
    "Codice": 100000239,
    "Descrizione": "SPAGNA",
    "Provincia": "ES",
    "DataFineVal": "",
    "ISO": "ESP"
  },
  {
    "Codice": 100000311,
    "Descrizione": "SRI LANKA (CEYLON)",
    "Provincia": "ES",
    "DataFineVal": "",
    "ISO": "LKA"
  },
  {
    "Codice": 100000536,
    "Descrizione": "STATI UNITI D'AMERICA",
    "Provincia": "ES",
    "DataFineVal": "",
    "ISO": "USA"
  },
  {
    "Codice": 100000246,
    "Descrizione": "STATO DELLA CITTA' DEL VATICANO",
    "Provincia": "ES",
    "DataFineVal": "",
    "ISO": "VAT"
  },
  {
    "Codice": 100000467,
    "Descrizione": "SUD SUDAN",
    "Provincia": "ES",
    "DataFineVal": "",
    "ISO": "SSD"
  },
  {
    "Codice": 100000454,
    "Descrizione": "SUDAFRICA",
    "Provincia": "ES",
    "DataFineVal": "",
    "ISO": "ZAF"
  },
  {
    "Codice": 100000455,
    "Descrizione": "SUDAN",
    "Provincia": "ES",
    "DataFineVal": "",
    "ISO": "SDN"
  },
  {
    "Codice": 100000616,
    "Descrizione": "SURINAME",
    "Provincia": "ES",
    "DataFineVal": "",
    "ISO": "SUR"
  },
  {
    "Codice": 100000240,
    "Descrizione": "SVEZIA",
    "Provincia": "ES",
    "DataFineVal": "",
    "ISO": "SWE"
  },
  {
    "Codice": 100000241,
    "Descrizione": "SVIZZERA",
    "Provincia": "ES",
    "DataFineVal": "",
    "ISO": "CHE"
  },
  {
    "Codice": 100000456,
    "Descrizione": "SWAZILAND",
    "Provincia": "ES",
    "DataFineVal": "",
    "ISO": "SWZ"
  },
  {
    "Codice": 100000362,
    "Descrizione": "TAGIKISTAN",
    "Provincia": "ES",
    "DataFineVal": "",
    "ISO": "TJK"
  },
  {
    "Codice": 100000363,
    "Descrizione": "TAIWAN",
    "Provincia": "ES",
    "DataFineVal": "",
    "ISO": "TWN"
  },
  {
    "Codice": 100000457,
    "Descrizione": "TANZANIA",
    "Provincia": "ES",
    "DataFineVal": "",
    "ISO": "TZA"
  },
  {
    "Codice": 100000349,
    "Descrizione": "THAILANDIA",
    "Provincia": "ES",
    "DataFineVal": "",
    "ISO": "THA"
  },
  {
    "Codice": 100000805,
    "Descrizione": "TIMOR",
    "Provincia": "ES",
    "DataFineVal": "",
    "ISO": "TLS"
  },
  {
    "Codice": 100000458,
    "Descrizione": "TOGO",
    "Provincia": "ES",
    "DataFineVal": "",
    "ISO": "TGO"
  },
  {
    "Codice": 100000806,
    "Descrizione": "TOKELAU",
    "Provincia": "ES",
    "DataFineVal": "",
    "ISO": "TKL"
  },
  {
    "Codice": 100000730,
    "Descrizione": "TONGA",
    "Provincia": "ES",
    "DataFineVal": "",
    "ISO": "TON"
  },
  {
    "Codice": 100000617,
    "Descrizione": "TRINIDAD E TOBAGO",
    "Provincia": "ES",
    "DataFineVal": "",
    "ISO": "TTO"
  },
  {
    "Codice": 100000460,
    "Descrizione": "TUNISIA",
    "Provincia": "ES",
    "DataFineVal": "",
    "ISO": "TUN"
  },
  {
    "Codice": 100000351,
    "Descrizione": "TURCHIA",
    "Provincia": "ES",
    "DataFineVal": "",
    "ISO": "TUR"
  },
  {
    "Codice": 100000364,
    "Descrizione": "TURKMENISTAN",
    "Provincia": "ES",
    "DataFineVal": "",
    "ISO": "TKM"
  },
  {
    "Codice": 100000810,
    "Descrizione": "TURKS",
    "Provincia": "ES",
    "DataFineVal": "",
    "ISO": "TUR"
  },
  {
    "Codice": 100000731,
    "Descrizione": "TUVALU",
    "Provincia": "ES",
    "DataFineVal": "",
    "ISO": "TUV"
  },
  {
    "Codice": 100000243,
    "Descrizione": "UCRAINA",
    "Provincia": "ES",
    "DataFineVal": "",
    "ISO": "UKR"
  },
  {
    "Codice": 100000461,
    "Descrizione": "UGANDA",
    "Provincia": "ES",
    "DataFineVal": "",
    "ISO": "UGA"
  },
  {
    "Codice": 100000244,
    "Descrizione": "UNGHERIA",
    "Provincia": "ES",
    "DataFineVal": "",
    "ISO": "HUN"
  },
  {
    "Codice": 100000618,
    "Descrizione": "URUGUAY",
    "Provincia": "ES",
    "DataFineVal": "",
    "ISO": "URY"
  },
  {
    "Codice": 100000357,
    "Descrizione": "UZBEKISTAN",
    "Provincia": "ES",
    "DataFineVal": "",
    "ISO": "UZB"
  },
  {
    "Codice": 100000732,
    "Descrizione": "VANUATU",
    "Provincia": "ES",
    "DataFineVal": "",
    "ISO": "VUT"
  },
  {
    "Codice": 100000619,
    "Descrizione": "VENEZUELA",
    "Provincia": "ES",
    "DataFineVal": "",
    "ISO": "VEN"
  },
  {
    "Codice": 100000812,
    "Descrizione": "VERGINI BRITANNICHE (ISOLE)",
    "Provincia": "ES",
    "DataFineVal": "",
    "ISO": "GBR"
  },
  {
    "Codice": 100000353,
    "Descrizione": "VIETNAM",
    "Provincia": "ES",
    "DataFineVal": "",
    "ISO": "VNM"
  },
  {
    "Codice": 100000815,
    "Descrizione": "WALLIS",
    "Provincia": "ES",
    "DataFineVal": "",
    "ISO": "WLF"
  },
  {
    "Codice": 100000354,
    "Descrizione": "YEMEN",
    "Provincia": "ES",
    "DataFineVal": "",
    "ISO": "YEM"
  },
  {
    "Codice": 100000464,
    "Descrizione": "ZAMBIA",
    "Provincia": "ES",
    "DataFineVal": "",
    "ISO": "ZMB"
  },
  {
    "Codice": 100000465,
    "Descrizione": "ZIMBABWE",
    "Provincia": "ES",
    "DataFineVal": "",
    "ISO": "ZWE"
  }
]
